gspreadmanager/__init__.py
gspreadmanager/config.py
gspreadmanager/connector.py
GSpreadManager-0.1.5.dist-info/METADATA
GSpreadManager-0.1.5.dist-info/WHEEL
GSpreadManager-0.1.5.dist-info/top_level.txt
GSpreadManager-0.1.5.dist-info/RECORD
