Metadata-Version: 2.1
Name: GSpreadManager
Version: 0.1.5
Summary: Un módulo de Python para gestionar y automatizar tareas en Google Sheets.
Home-page: https://github.com/PabloAlaniz/GSpreadManager
Author: PabloAlaniz
Author-email: pablo@culturainteractiva.com
Classifier: Development Status :: 3 - Alpha
Classifier: Intended Audience :: Developers
Classifier: License :: OSI Approved :: MIT License
Classifier: Programming Language :: Python :: 3
Classifier: Programming Language :: Python :: 3.7
Classifier: Programming Language :: Python :: 3.8
Classifier: Programming Language :: Python :: 3.9
Classifier: Operating System :: OS Independent
Requires-Python: >=3.7
Requires-Dist: gspread >=3.0
Requires-Dist: oauth2client >=4.0
Requires-Dist: pandas >=1.2.4
